cddns/__init__.py
cddns/config.py
cddns/dnspod.py
cddns/email.py
cddns/ftqq.py
cddns/ip.py
cddns/log.py
cddns/record.py
cddns-0.1.dist-info/LICENSE
cddns-0.1.dist-info/METADATA
cddns-0.1.dist-info/WHEEL
cddns-0.1.dist-info/top_level.txt
cddns-0.1.dist-info/RECORD
