Metadata-Version: 2.1
Name: cddns
Version: 0.1
Summary: 支持多域名的ddns脚本
Home-page: https://github.com/chr233/pyddns
Author: Chr_
Author-email: chr@chrxw.com
License: UNKNOWN
Platform: UNKNOWN
Classifier: Programming Language :: Python :: 3
Classifier: License :: OSI Approved :: GNU Affero General Public License v3 or later (AGPLv3+)
Classifier: Operating System :: OS Independent
Requires-Dist: requests
Requires-Dist: toml
